
{
    "ID": 0,
    "key": "group_552fbd209f99e",
    "title": "Teaser",
    "location": [
        [
            {
                "param": "post_type",
                "operator": "!=",
                "value": "sidebar"
            }
        ],
        [
            {
                "param": "taxonomy",
                "operator": "==",
                "value": "all"
            }
        ]
    ],
    "menu_order": 0,
    "position": "normal",
    "style": "default",
    "label_placement": "top",
    "instruction_placement": "label",
    "hide_on_screen": "",
    "active": 1,
    "description": "",
    "local": "php",
    "fields": [
        {
            "ID": 0,
            "key": "field_55363f81d481d",
            "label": "Indikatoren",
            "name": "teaser_indicator",
            "prefix": "",
            "type": "true_false",
            "value": null,
            "menu_order": 0,
            "instructions": "Die Indikatoren werden nur ausgegeben, wenn mehr als 1 Bild hochgeladen wurde. Falls du die Indikatoren bei mehreren Bildern nicht angezeigen willst, aktiviere dieses Feld.",
            "required": 0,
            "id": "",
            "class": "",
            "conditional_logic": 0,
            "parent": "group_552fbd209f99e",
            "wrapper": {
                "width": 25,
                "class": "",
                "id": ""
            },
            "_name": "teaser_indicator",
            "_input": "",
            "_valid": 1,
            "message": "ausblenden",
            "default_value": 0
        },
        {
            "ID": 0,
            "key": "field_5536410f116d9",
            "label": "Pfeile",
            "name": "teaser_arrows",
            "prefix": "",
            "type": "true_false",
            "value": null,
            "menu_order": 1,
            "instructions": "Die Pfeile werden nur ausgegeben, wenn mehr als 1 Bild hochgeladen wurde. Falls du die Pfeile bei mehreren Bildern nicht angezeigen willst, aktiviere dieses Feld.",
            "required": 0,
            "id": "",
            "class": "",
            "conditional_logic": 0,
            "parent": "group_552fbd209f99e",
            "wrapper": {
                "width": 25,
                "class": "",
                "id": ""
            },
            "_name": "teaser_arrows",
            "_input": "",
            "_valid": 1,
            "message": "ausblenden",
            "default_value": 0
        },
        {
            "ID": 0,
            "key": "field_553647bab6343",
            "label": "Geschwindikeit \/ Intervall",
            "name": "teaser_interval",
            "prefix": "",
            "type": "number",
            "value": null,
            "menu_order": 2,
            "instructions": "Nach wievielen millisekunden soll der n\u00e4chste Slide erscheinen?",
            "required": 0,
            "id": "",
            "class": "",
            "conditional_logic": 0,
            "parent": "group_552fbd209f99e",
            "wrapper": {
                "width": 25,
                "class": "",
                "id": ""
            },
            "_name": "teaser_interval",
            "_input": "",
            "_valid": 1,
            "default_value": 8000,
            "placeholder": "",
            "prepend": "",
            "append": "ms",
            "min": "",
            "max": "",
            "step": "",
            "readonly": 0,
            "disabled": 0
        },
        {
            "ID": 0,
            "key": "field_55364765b6cce",
            "label": "Fade Effekt",
            "name": "teaser_fade",
            "prefix": "",
            "type": "true_false",
            "value": null,
            "menu_order": 3,
            "instructions": "",
            "required": 0,
            "id": "",
            "class": "",
            "conditional_logic": 0,
            "parent": "group_552fbd209f99e",
            "wrapper": {
                "width": 25,
                "class": "",
                "id": ""
            },
            "_name": "teaser_fade",
            "_input": "",
            "_valid": 1,
            "message": "aktivieren",
            "default_value": 0
        },
        {
            "ID": 0,
            "key": "field_552fbd3036749",
            "label": "Bilder",
            "name": "teaser_image",
            "prefix": "",
            "type": "repeater",
            "value": null,
            "menu_order": 4,
            "instructions": "Solltest du nur 1 Bild hochladen, wird die Slide-Funktion automatisch deaktiviert.",
            "required": 0,
            "id": "",
            "class": "",
            "conditional_logic": 0,
            "parent": "group_552fbd209f99e",
            "wrapper": {
                "width": "",
                "class": "",
                "id": ""
            },
            "_name": "teaser_image",
            "_input": "",
            "_valid": 1,
            "min": "",
            "max": "",
            "layout": "block",
            "button_label": "Bild hinzuf\u00fcgen",
            "sub_fields": [
                {
                    "ID": 0,
                    "key": "field_5536747cec084",
                    "label": "Hintergrundfarbe",
                    "name": "background",
                    "prefix": "",
                    "type": "color_picker",
                    "value": null,
                    "menu_order": 0,
                    "instructions": "",
                    "required": 0,
                    "id": "",
                    "class": "",
                    "conditional_logic": 0,
                    "parent": "field_552fbd3036749",
                    "wrapper": {
                        "width": 15,
                        "class": "",
                        "id": ""
                    },
                    "_name": "background",
                    "_input": "",
                    "_valid": 1,
                    "default_value": ""
                },
                {
                    "ID": 0,
                    "key": "field_55363d7045078",
                    "label": "Bild",
                    "name": "image",
                    "prefix": "",
                    "type": "image",
                    "value": null,
                    "menu_order": 1,
                    "instructions": "",
                    "required": 0,
                    "id": "",
                    "class": "",
                    "conditional_logic": 0,
                    "parent": "field_552fbd3036749",
                    "wrapper": {
                        "width": 75,
                        "class": "",
                        "id": ""
                    },
                    "_name": "image",
                    "_input": "",
                    "_valid": 1,
                    "return_format": "array",
                    "preview_size": "thumbnail",
                    "library": "all",
                    "min_width": "",
                    "min_height": "",
                    "min_size": "",
                    "max_width": "",
                    "max_height": "",
                    "max_size": "",
                    "mime_types": ""
                },
                {
                    "ID": 0,
                    "key": "field_55363d7945079",
                    "label": "Text",
                    "name": "text",
                    "prefix": "",
                    "type": "wysiwyg",
                    "value": null,
                    "menu_order": 2,
                    "instructions": "",
                    "required": 0,
                    "id": "",
                    "class": "",
                    "conditional_logic": 0,
                    "parent": "field_552fbd3036749",
                    "wrapper": {
                        "width": "",
                        "class": "",
                        "id": ""
                    },
                    "_name": "text",
                    "_input": "",
                    "_valid": 1,
                    "default_value": "",
                    "tabs": "all",
                    "toolbar": "full",
                    "media_upload": 1
                },
                {
                    "ID": 0,
                    "key": "field_564c77539799a",
                    "label": "Link",
                    "name": "url",
                    "prefix": "",
                    "type": "url",
                    "value": null,
                    "menu_order": 3,
                    "instructions": "Soll das komplette Bild verlinkt werden? Bitte gebe hier die URL an, auf welche verlinkt werden soll.",
                    "required": 0,
                    "id": "",
                    "class": "",
                    "conditional_logic": 0,
                    "parent": "field_552fbd3036749",
                    "wrapper": {
                        "width": 50,
                        "class": "",
                        "id": ""
                    },
                    "_name": "url",
                    "_input": "",
                    "_valid": 1,
                    "default_value": "",
                    "placeholder": "",
                    "prepend": "",
                    "append": "",
                    "maxlength": "",
                    "readonly": 0,
                    "disabled": 0
                },
                {
                    "ID": 0,
                    "key": "field_564c77ccbe0a9",
                    "label": "Externer Link",
                    "name": "external",
                    "prefix": "",
                    "type": "true_false",
                    "value": null,
                    "menu_order": 4,
                    "instructions": "Mit dieser Option wird der Link in einem neuen Fenster ge\u00f6ffnet.",
                    "required": 0,
                    "id": "",
                    "class": "",
                    "conditional_logic": 0,
                    "parent": "field_552fbd3036749",
                    "wrapper": {
                        "width": 25,
                        "class": "",
                        "id": ""
                    },
                    "_name": "external",
                    "_input": "",
                    "_valid": 1,
                    "message": "Ja",
                    "default_value": 0
                },
                {
                    "ID": 0,
                    "key": "field_564c77e53896e",
                    "label": "Nofollow",
                    "name": "nofollow",
                    "prefix": "",
                    "type": "true_false",
                    "value": null,
                    "menu_order": 5,
                    "instructions": "Mit dieser Option wird dem Link das Attribut rel=\"nofollow\" hinzugef\u00fcgt.",
                    "required": 0,
                    "id": "",
                    "class": "",
                    "conditional_logic": 0,
                    "parent": "field_552fbd3036749",
                    "wrapper": {
                        "width": 25,
                        "class": "",
                        "id": ""
                    },
                    "_name": "nofollow",
                    "_input": "",
                    "_valid": 1,
                    "message": "Ja",
                    "default_value": 0
                }
            ]
        }
    ]
}